hebrewtools/__init__.py
hebrewtools/functions.py
hebrewtools-0.1.0.dist-info/LICENSE.txt
hebrewtools-0.1.0.dist-info/METADATA
hebrewtools-0.1.0.dist-info/WHEEL
hebrewtools-0.1.0.dist-info/top_level.txt
hebrewtools-0.1.0.dist-info/RECORD
