Metadata-Version: 2.1
Name: hebrewtools
Version: 0.1.0
Summary: Useful tools for working with vocalized Hebrew text in Python
Home-page: https://github.com/gngpostalsrvc/hebrewtools
Author: Aren Wilson-Wright
Author-email: wilsonwright.a@gmail.com
License: MIT
Download-URL: https://pypi.org/project/hebrewtools/
Keywords: Biblical Hebrew,vocalization,normalization
Platform: UNKNOWN
License-File: LICENSE.txt
